tsquad/__init__.py
tsquad/generate_c_nodes_weights_header.py
tsquad/generate_py_nodes_weights.py
tsquad/nodes_weights.py
tsquad/shanks.py
tsquad/tsconfig.py
tsquad/tsquad_py.py
tsquad-0.2.5.dist-info/LICENSE
tsquad-0.2.5.dist-info/METADATA
tsquad-0.2.5.dist-info/WHEEL
tsquad-0.2.5.dist-info/RECORD
