Metadata-Version: 2.1
Name: tsquad
Version: 0.2.5
Summary: numeric quadrature using the Tanh-Sinh variable transformation
Home-page: https://github.com/cimatosa/tsquad
License: MIT
Keywords: numerical-integration,tanh-sinh-method,Fourier-transform,infinite-series
Author: Richard Hartmann
Author-email: richard.hartmann@tu-dresden.de
Requires-Python: >=3.9,<4.0
Classifier: Intended Audience :: Science/Research
Classifier: License :: OSI Approved :: MIT License
Classifier: Programming Language :: Python :: 3
Classifier: Programming Language :: Python :: 3.9
Classifier: Programming Language :: Python :: 3.10
Classifier: Programming Language :: Python :: 3.11
Classifier: Topic :: Scientific/Engineering :: Mathematics
Classifier: Topic :: Scientific/Engineering :: Physics
Classifier: Topic :: Software Development :: Libraries :: Python Modules
Requires-Dist: mpmath (>=1.2.1,<2.0.0)
Requires-Dist: numpy (>=1.22.2,<2.0.0)
Project-URL: Repository, https://github.com/cimatosa/tsquad
